Metadata-Version: 1.2
Name: Flask-Philo-Core
Version: 0.5.0
Summary: Flask extension that provides a common framework for webapps
Home-page: https://github.com/Riffstation/flask-philo
Author: Manuel Ignacio Franco Galeano
Author-email: maigfrga@gmail.com
License: Apache
Keywords: flask REST framework
Platform: UNKNOWN
Classifier: Development Status :: 4 - Beta
Classifier: Intended Audience :: Developers
Classifier: Topic :: Software Development
Classifier: Framework :: Flask
Classifier: Programming Language :: Python :: 3
Requires-Python: >=3.6
